orbit_boost/__init__.py
orbit_boost/_linear_warmstart.py
orbit_boost/_oblique.py
orbit_boost/_sampling.py
orbit_boost/_version.py
orbit_boost/orbit_boost.py
orbit_boost-0.1.1.post1.dist-info/METADATA
orbit_boost-0.1.1.post1.dist-info/WHEEL
orbit_boost-0.1.1.post1.dist-info/licenses/LICENSE
orbit_boost-0.1.1.post1.dist-info/RECORD
